{
  "nodes": [
    {
      "id": "Jade",
      "group": 0
    },
    {
      "id": "Dragon scimitar",
      "group": 0
    },
    {
      "id": "Iron bar",
      "group": 0
    },
    {
      "id": "Shark",
      "group": 0
    },
    {
      "id": "Lantern lens",
      "group": 0
    },
    {
      "id": "Zamorak cape",
      "group": 0
    },
    {
      "id": "Zamorak godsword",
      "group": 0
    },
    {
      "id": "Potato cactus",
      "group": 0
    },
    {
      "id": "Necromancer hood",
      "group": 0
    },
    {
      "id": "Iban's staff",
      "group": 0
    },
    {
      "id": "Stake",
      "group": 0
    },
    {
      "id": "Dramen staff",
      "group": 0
    },
    {
      "id": "Silverlight",
      "group": 0
    },
    {
      "id": "Kayle's chargebow",
      "group": 0
    },
    {
      "id": "Bearhead",
      "group": 0
    },
    {
      "id": "Ancient body",
      "group": 0
    },
    {
      "id": "Astral rune",
      "group": 0
    },
    {
      "id": "Earth rune",
      "group": 0
    },
    {
      "id": "Rune essence",
      "group": 0
    },
    {
      "id": "Bronze hatchet",
      "group": 0
    },
    {
      "id": "Mithril longsword",
      "group": 0
    },
    {
      "id": "H.a.m. boots",
      "group": 0
    },
    {
      "id": "Farming hood",
      "group": 0
    },
    {
      "id": "Rune pickaxe",
      "group": 0
    },
    {
      "id": "Agility cape",
      "group": 0
    },
    {
      "id": "Pendant of Construction",
      "group": 0
    },
    {
      "id": "Willow logs",
      "group": 0
    },
    {
      "id": "Tinderbox",
      "group": 0
    },
    {
      "id": "Constitution hood",
      "group": 0
    },
    {
      "id": "Fletching flask",
      "group": 0
    },
    {
      "id": "Fishing rod",
      "group": 0
    },
    {
      "id": "Slayer bell",
      "group": 0
    },
    {
      "id": "Hunter's chestpiece",
      "group": 0
    },
    {
      "id": "Rune platebody",
      "group": 0
    },
    {
      "id": "Watering can",
      "group": 0
    },
    {
      "id": "Agility lamp",
      "group": 0
    },
    {
      "id": "Thieving hood",
      "group": 0
    },
    {
      "id": "Gold ore",
      "group": 0
    },
    {
      "id": "Adamant arrow",
      "group": 0
    },
    {
      "id": "Santa hat",
      "group": 0
    },
    {
      "id": "Wizard shield",
      "group": 0
    },
    {
      "id": "Crafting",
      "group": 1
    },
    {
      "id": "Attack",
      "group": 1
    },
    {
      "id": "Smithing",
      "group": 1
    },
    {
      "id": "Cooking",
      "group": 1
    },
    {
      "id": "Magic",
      "group": 1
    },
    {
      "id": "Fishing",
      "group": 1
    },
    {
      "id": "Herblore",
      "group": 1
    },
    {
      "id": "Defence",
      "group": 1
    },
    {
      "id": "Mining",
      "group": 1
    },
    {
      "id": "Agility",
      "group": 1
    },
    {
      "id": "Farming",
      "group": 1
    },
    {
      "id": "Thieving",
      "group": 1
    },
    {
      "id": "Prayer",
      "group": 1
    },
    {
      "id": "Ranged",
      "group": 1
    },
    {
      "id": "Construction",
      "group": 1
    },
    {
      "id": "Runecrafting",
      "group": 1
    },
    {
      "id": "Slayer",
      "group": 1
    },
    {
      "id": "Hunter",
      "group": 1
    },
    {
      "id": "Fletching",
      "group": 1
    },
    {
      "id": "Strength",
      "group": 1
    },
    {
      "id": "Hitpoints",
      "group": 1
    },
    {
      "id": "Woodcutting",
      "group": 1
    },
    {
      "id": "Firemaking",
      "group": 1
    }
  ],
  "links": [
    {
      "source": "Jade",
      "target": "Crafting",
      "value": 5
    },
    {
      "source": "Jade",
      "target": "Mining",
      "value": 5
    },
    {
      "source": "Dragon scimitar",
      "target": "Attack",
      "value": 5
    },
    {
      "source": "Dragon scimitar",
      "target": "Slayer",
      "value": 5
    },
    {
      "source": "Iron bar",
      "target": "Smithing",
      "value": 5
    },
    {
      "source": "Iron bar",
      "target": "Mining",
      "value": 5
    },
    {
      "source": "Shark",
      "target": "Cooking",
      "value": 5
    },
    {
      "source": "Shark",
      "target": "Fishing",
      "value": 5
    },
    {
      "source": "Lantern lens",
      "target": "Crafting",
      "value": 5
    },
    {
      "source": "Zamorak cape",
      "target": "Magic",
      "value": 5
    },
    {
      "source": "Zamorak godsword",
      "target": "Attack",
      "value": 5
    },
    {
      "source": "Potato cactus",
      "target": "Cooking",
      "value": 5
    },
    {
      "source": "Potato cactus",
      "target": "Herblore",
      "value": 5
    },
    {
      "source": "Necromancer hood",
      "target": "Crafting",
      "value": 5
    },
    {
      "source": "Necromancer hood",
      "target": "Magic",
      "value": 5
    },
    {
      "source": "Necromancer hood",
      "target": "Defence",
      "value": 5
    },
    {
      "source": "Necromancer hood",
      "target": "Prayer",
      "value": 5
    },
    {
      "source": "Iban's staff",
      "target": "Magic",
      "value": 5
    },
    {
      "source": "Stake",
      "target": "Attack",
      "value": 5
    },
    {
      "source": "Stake",
      "target": "Strength",
      "value": 5
    },
    {
      "source": "Dramen staff",
      "target": "Crafting",
      "value": 5
    },
    {
      "source": "Dramen staff",
      "target": "Magic",
      "value": 5
    },
    {
      "source": "Silverlight",
      "target": "Attack",
      "value": 5
    },
    {
      "source": "Silverlight",
      "target": "Defence",
      "value": 5
    },
    {
      "source": "Silverlight",
      "target": "Strength",
      "value": 5
    },
    {
      "source": "Kayle's chargebow",
      "target": "Ranged",
      "value": 5
    },
    {
      "source": "Bearhead",
      "target": "Defence",
      "value": 5
    },
    {
      "source": "Ancient body",
      "target": "Ranged",
      "value": 5
    },
    {
      "source": "Astral rune",
      "target": "Prayer",
      "value": 5
    },
    {
      "source": "Astral rune",
      "target": "Runecrafting",
      "value": 5
    },
    {
      "source": "Astral rune",
      "target": "Crafting",
      "value": 5
    },
    {
      "source": "Astral rune",
      "target": "Magic",
      "value": 5
    },
    {
      "source": "Astral rune",
      "target": "Mining",
      "value": 5
    },
    {
      "source": "Earth rune",
      "target": "Prayer",
      "value": 5
    },
    {
      "source": "Earth rune",
      "target": "Runecrafting",
      "value": 5
    },
    {
      "source": "Earth rune",
      "target": "Crafting",
      "value": 5
    },
    {
      "source": "Earth rune",
      "target": "Magic",
      "value": 5
    },
    {
      "source": "Earth rune",
      "target": "Mining",
      "value": 5
    },
    {
      "source": "Rune essence",
      "target": "Prayer",
      "value": 5
    },
    {
      "source": "Rune essence",
      "target": "Runecrafting",
      "value": 5
    },
    {
      "source": "Rune essence",
      "target": "Crafting",
      "value": 5
    },
    {
      "source": "Rune essence",
      "target": "Magic",
      "value": 5
    },
    {
      "source": "Rune essence",
      "target": "Mining",
      "value": 5
    },
    {
      "source": "Bronze hatchet",
      "target": "Attack",
      "value": 5
    },
    {
      "source": "Bronze hatchet",
      "target": "Smithing",
      "value": 5
    },
    {
      "source": "Bronze hatchet",
      "target": "Woodcutting",
      "value": 5
    },
    {
      "source": "Mithril longsword",
      "target": "Attack",
      "value": 5
    },
    {
      "source": "Mithril longsword",
      "target": "Smithing",
      "value": 5
    },
    {
      "source": "H.a.m. boots",
      "target": "Thieving",
      "value": 5
    },
    {
      "source": "Farming hood",
      "target": "Farming",
      "value": 5
    },
    {
      "source": "Rune pickaxe",
      "target": "Attack",
      "value": 5
    },
    {
      "source": "Rune pickaxe",
      "target": "Mining",
      "value": 5
    },
    {
      "source": "Agility cape",
      "target": "Agility",
      "value": 5
    },
    {
      "source": "Pendant of Construction",
      "target": "Construction",
      "value": 5
    },
    {
      "source": "Willow logs",
      "target": "Woodcutting",
      "value": 5
    },
    {
      "source": "Willow logs",
      "target": "Firemaking",
      "value": 5
    },
    {
      "source": "Tinderbox",
      "target": "Woodcutting",
      "value": 5
    },
    {
      "source": "Tinderbox",
      "target": "Firemaking",
      "value": 5
    },
    {
      "source": "Constitution hood",
      "target": "Hitpoints",
      "value": 5
    },
    {
      "source": "Fletching flask",
      "target": "Crafting",
      "value": 5
    },
    {
      "source": "Fletching flask",
      "target": "Fletching",
      "value": 5
    },
    {
      "source": "Fishing rod",
      "target": "Fishing",
      "value": 5
    },
    {
      "source": "Slayer bell",
      "target": "Slayer",
      "value": 5
    },
    {
      "source": "Hunter's chestpiece",
      "target": "Hunter",
      "value": 5
    },
    {
      "source": "Rune platebody",
      "target": "Defence",
      "value": 5
    },
    {
      "source": "Watering can",
      "target": "Herblore",
      "value": 5
    },
    {
      "source": "Watering can",
      "target": "Farming",
      "value": 5
    },
    {
      "source": "Agility lamp",
      "target": "Agility",
      "value": 5
    },
    {
      "source": "Thieving hood",
      "target": "Thieving",
      "value": 5
    },
    {
      "source": "Gold ore",
      "target": "Mining",
      "value": 5
    },
    {
      "source": "Adamant arrow",
      "target": "Attack",
      "value": 5
    },
    {
      "source": "Adamant arrow",
      "target": "Ranged",
      "value": 5
    },
    {
      "source": "Adamant arrow",
      "target": "Fletching",
      "value": 5
    },
    {
      "source": "Santa hat",
      "target": "Defence",
      "value": 5
    },
    {
      "source": "Wizard shield",
      "target": "Magic",
      "value": 5
    },
    {
      "source": "Wizard shield",
      "target": "Defence",
      "value": 5
    }
  ]
}